constrained_values/__init__.py
constrained_values/constants.py
constrained_values/constrained_value_types.py
constrained_values/response.py
constrained_values/status.py
constrained_values/strategies.py
constrained_values/value.py
constrained_values-0.1.1.dist-info/licenses/LICENSE
constrained_values-0.1.1.dist-info/METADATA
constrained_values-0.1.1.dist-info/WHEEL
constrained_values-0.1.1.dist-info/top_level.txt
constrained_values-0.1.1.dist-info/RECORD
