Metadata-Version: 2.4
Name: constrained-values
Version: 0.1.1
Summary: A Python library for creating type-safe, self-validating value objects using a powerful transformation and validation pipeline.
Author-email: Michael Lindre <cvl@oodesigns.com>
License: MIT License
Project-URL: Homepage, https://github.com/OODesigns/constrained-values
Project-URL: Issues, https://github.com/OODesigns/constrained-values/issues
Keywords: validation,value-object,constraints,types,enum,range
Classifier: Programming Language :: Python :: 3
Classifier: Programming Language :: Python :: 3.10
Classifier: Programming Language :: Python :: 3.11
Classifier: Programming Language :: Python :: 3.12
Classifier: License :: OSI Approved :: MIT License
Classifier: Operating System :: OS Independent
License-File: LICENSE
Dynamic: license-file
